{
  "project_info": {
    "project_number": "956816836555",
    "firebase_url": "https://dementia-1296b.firebaseio.com",
    "project_id": "dementia-1296b",
    "storage_bucket": "dementia-1296b.appspot.com"
  },
  "client": [
    {
      "client_info": {
        "mobilesdk_app_id": "1:956816836555:android:3a5386f248c2dd98",
        "android_client_info": {
          "package_name": "kr.co.inergy.selftest"
        }
      },
      "oauth_client": [
        {
          "client_id": "956816836555-5ff8p5pe1g4vl7ldgb1n8gikvf7gtsa6.apps.googleusercontent.com",
          "client_type": 3
        }
      ],
      "api_key": [
        {
          "current_key": "AIzaSyD2TKLZS4ZiW9WezYGm88LXOme_6Mh5EOg"
        }
      ],
      "services": {
        "analytics_service": {
          "status": 1
        },
        "appinvite_service": {
          "status": 1,
          "other_platform_oauth_client": []
        },
        "ads_service": {
          "status": 2
        }
      }
    }
  ],
  "configuration_version": "1"
}